fmbt/1_generate_data.ipynb
fmbt/2_deploy_model.ipynb
fmbt/3_run_inference.ipynb
fmbt/4_model_metric_analysis.ipynb
fmbt/5_cleanup.ipynb
fmbt/__init__.py
fmbt/config_filepath.txt
fmbt/configs/config-llama2-13b-inf2-g5-p4d-v1.yml
fmbt/configs/config-llama2-70b-g5-p4d-tgi.yml
fmbt/configs/config-llama2-70b-g5-p4d-trt.yml
fmbt/configs/config-mistral-7b-tgi-g5.yml
fmbt/globals.py
fmbt/main.py
fmbt/prompt_template/prompt_template.txt
fmbt/requirements.txt
fmbt/scripts/jumpstart.py
fmbt/scripts/p4d_djl.py
fmbt/scripts/p4d_hf_tgi.py
fmbt/scripts/p4d_serving.properties
fmbt/utils.py
fmbt-1.0.7.dist-info/entry_points.txt
fmbt-1.0.7.dist-info/LICENSE
fmbt-1.0.7.dist-info/METADATA
fmbt-1.0.7.dist-info/WHEEL
fmbt-1.0.7.dist-info/RECORD
