Metadata-Version: 2.1
Name: fmbt
Version: 1.0.7
Summary: Benchmark performance of **any model** on **any supported instance type** on Amazon SageMaker.
Author: Amit Arora
Author-email: aroraai@amazon.com
Requires-Python: >=3.11,<4.0
Classifier: Programming Language :: Python :: 3
Classifier: Programming Language :: Python :: 3.11
Classifier: Programming Language :: Python :: 3.12
Requires-Dist: boto3 (>=1.34.32,<2.0.0)
Requires-Dist: datasets (==2.16.1)
Requires-Dist: ipywidgets (==8.1.1)
Requires-Dist: jupyter (>=1.0.0,<2.0.0)
Requires-Dist: pandas (==2.1.4)
Requires-Dist: papermill (>=2.5.0,<3.0.0)
Requires-Dist: pyyaml
Requires-Dist: requests (>=2.31.0,<3.0.0)
Requires-Dist: sagemaker (==2.203.0)
Requires-Dist: seaborn (==0.13.1)
Requires-Dist: tomark (==0.1.4)
Requires-Dist: transformers (==4.36.2)
